setup.py
dxdiff/__init__.py
dxdiff/bimap.py
dxdiff/diff.py
dxdiff/dxdiff
dxdiff/editscript.py
dxdiff/fmes.py
dxdiff/lcs.py
dxdiff/utils.py
dxdiff.egg-info/PKG-INFO
dxdiff.egg-info/SOURCES.txt
dxdiff.egg-info/dependency_links.txt
dxdiff.egg-info/top_level.txt