Metadata-Version: 2.1
Name: dxdiff
Version: 1.2.2
Summary: An XML aware diff tool
Home-page: http://candylab.org
Author: The ICOM team and collaborators
Author-email: contact@candylab.org
License: UNKNOWN
Platform: UNKNOWN
